setup.py
awsud_probability/Binomialdistribution.py
awsud_probability/Gaussiandistribution.py
awsud_probability/Generaldistribution.py
awsud_probability/__init__.py
awsud_probability.egg-info/PKG-INFO
awsud_probability.egg-info/SOURCES.txt
awsud_probability.egg-info/dependency_links.txt
awsud_probability.egg-info/not-zip-safe
awsud_probability.egg-info/top_level.txt