Metadata-Version: 1.0
Name: awsud-probability
Version: 0.1
Summary: Gaussian and Binomial distributions
Home-page: UNKNOWN
Author: Raghav Bansal
Author-email: UNKNOWN
License: UNKNOWN
Platform: UNKNOWN
